{"current":{"layout_style":"normal","classic_header":false,"rtl":false,"catalog-mode":false,"top-information-bar":false,"favicon":"shopify:\/\/shop_images\/FG_-_Print_Transparent_2.png","show_sticky_header":true,"show_sticky_arrow":true,"enable_site_animation":true,"site_animation_mobile":true,"ajax_cart":true,"enable_wishlist":true,"christmas":false,"christmas_style":"style1","dis_br_webpage":false,"dis_br_colpage":false,"dis_br_productpage":true,"terms_checkbox":true,"terms_text":"I agree with the terms and conditions","enable_age_varification":false,"enable_birthdate":false,"agevari_popup_bg":"","free_ship":"90","free_ship_msg":"Add $, Get Free Shipping","got_free_ship":"Congratulations! Your order is eligible for FREE Delivery.","estimate_ship":"4\/10","estimate_shipping_msg":"Estimated delivery between [startdate] and [enddate].","secondary_image":true,"enable_quickshop":true,"show_cart_btn":true,"show_cart_btn_mobile":true,"display_countdown":false,"show_color_swatch":true,"color_type":"color","color_size":"small","color_style":"rounded","pr_lbl":true,"select_label_style":"rounded","lbl_txt":"#fff","sale_lbl":true,"sale_label_style":"salelabel","lbl_sale_cl":"#ff708e","pr_label1":"new","pr_label1_cl":"#000","pr_label2":"Hot","pr_label2_cl":"#e9a400","pr_label3":"Popular","pr_label3_cl":"#81d53d","base_font":"montserrat_n4","type_base_size":17,"header_font":"montserrat_n5","type_header_base_size":32,"header_case":"capitalize","section-font-weight":"500","nav_size":14,"nav_ttl":16,"font-weight":"regular","nav_case":"uppercase","slide_title":55,"slide_title_weight":"700","slide_title_case":"uppercase","slide_sub_title":21,"slide_subtitle_weight":"400","slide_subtitle_case":"uppercase","page_title_text_size":22,"product_title_text_size":29,"color_body_bg":"#bdb9b9","color_body_text":"#ffffff","color_text":"#ffffff","color_links":"#79ff6f","color_borders":"#ffffff","color_text_field":"#ffffff","color_text_field_text":"#000000","color_button":"#ffffff","color_button_text":"#000000","color_small_button":"#ededed","color_small_button_text":"#000000","link_btn":"#79ff6f","pr_btn":"#ffffff","pr_btn_text":"#000000","color_bg":"#79ff6f","annouance_color_text":"#000000","top_header_clr":"#79ff6f","top_header_text_clr":"#000000","main_header_bg_clr":"#000000","main_hd_btm_border":"#ffffff","icons_clr":"#79ff6f","cart_count":"#fff","cl_navbar_link":"#bdb9b9","cl_navbar_link_hv":"#79ff6f","cl_icons_clr":"#ffffff","cl_cart_count":"#ffffff","cd_bg":"#000000","cd_bdr":"#eeeeee","cd_txt":"#ffffff","cp_bg":"#000000","cp_txt":"#ffffff","search_bg":"#fff","search_txt":"#333","top_bar_bdr":"#111","top_bar_bg_clr":"#000","top_bar_text_clr":"#eee","navbar_bg":"#000000","navbar_link":"#ffffff","navbar_link_hv":"#79ff6f","navbar_link_bghv":"#000000","navbar_bdr":"#000000","nav_link_lbl":"#ffffff","nav_link_lbl1":"#f00","nav_link_lbl2":"#79ff6f","nav_link_lbl3":"#7fbf10","nav_link_lbl4":"#d0a306","nav_link_lbl5":"#af4de2","nav_mm_bg":"#000000","nav_mm_title":"#ffffff","nav_mm_link":"#d4cece","nav_mm_link_hv":"#79ff6f","nav_dd_link":"#000000","nav_dd_link_bg":"#ffffff","nav_dd_link_hv":"#000","nav_dd_divider":"#eeeeee","nav_dd_link_bghv":"#eee","mobile_nav_bg":"#000000","navigation_text":"#bdb9b9","border":"#303838","subnav_color_shade":"darken","newsletter_bg_clr":"#000000","newsletter_text_clr":"#888585","newsletter_border_clr":"#000000","newsletter_button_clr":"#000","newsletter_button_hover_clr":"#444444","social_icon_colors":"#79ff6f","footer_bg_clr":"#000000","footer_top_bdr":"#000000","footer_text_clr":"#818989","footer_title_clr":"#ffffff","footer_border_clr":"#1c1717","icon_colors":"#ffffff","scroll_icon_colors":"#79ff6f","color_slideshow_image_overlay":"#000000","image_slideshow_overlay_opacity":"0","slide_text_clr":"#ffffff","slide_text_shadow":"rgba(0,0,0,0)","slide_btn":"#79ff6f","slide_btn_txt":"#333333","display_overlay":false,"slide_overlay_clr":"#ffffff","display_overlay_border":false,"slide_border_clr":"#000000","color_image_overlay_text":"rgba(0,0,0,0)","color_image_overlay":"#000000","image_overlay_opacity":"0","bnr_ttl":"#ffffff","bnr_ttl_bg":"#ffffff","pr_tab_txt":"#929292","pr_tab_bg":"#f6f6f6","pr_tab_brd":"#eee","pr_tab_txt_ac":"#929292","pr_tab_bg_ac":"#f6f6f6","pr_tab_brd_ac":"#eee","header_bg_clr":"rgba(0,0,0,0)","header_text_clr":"#ffffff","page_hdr_btm_bdr":"rgba(0,0,0,0)","br_bg":"#000000","br_txt":"#ffffff","color_product_title":"#ffffff","color_price_text":"#ffffff","color_sale_text":"#79ff6f","product_tick_color":"#ee8e8e","product_review_color":"#ff9500","Products_countdown_text":"#ffffff","Products_countdown_text_bg":"#000000","Products_countdown_text_bg_opacity":"0.25","product_tab_text_color":"#929292","product_tab_active_text_color":"#79ff6f","product_zoom_video":"#111","product_zoom_video_bg":"#eee","quantity_msg":"#79ff6f","countdown_text":"#000000","order_text":"#79ff6f","visitors_count":"#79ff6f","active_swatch_clr":"#79ff6f","buynow_btn_text":"#000000","buynow_btn":"#79ff6f","social-share-icon":"#ffffff","cart_bg":"#79ff6f","cart_text":"#000000","cart_qty_bdr":"#eee","cart_btn":"#eee","cart_btn_text":"#000000","product_detail_tab_border":"#e8e9eb","product_detail_tab_text_color":"#ffffff","product_detail_tab_active_text_color":"#ffffff","show_multiple_currencies":true,"currency_format":"money_format","supported_currencies":"AUD","default_currency":"AUD","mbl_lbl_crn":"SELECT CURRENCY","show_language":false,"default_language":"English","languages":"","mbl_lbl_lang":"SELECT LANGUAGE","share_image":"","share_facebook":false,"share_twitter":false,"share_google":false,"share_pinterest":false,"share_email":false,"social_twitter_link":"","social_facebook_link":"https:\/\/www.facebook.com\/Frog-Grips-114720846967132\/","social_pinterest_link":"","social_instagram_link":"https:\/\/www.instagram.com\/Frog_grips\/","social_tumblr_link":"","social_youtube_link":"","social_vimeo_link":"","show_notification":true,"hide_notification_mb":true,"notify_collection":"","notify_msg":"Someone liked and bought","fake_time":true,"time_msg":"Minutes Ago","location_msg":"From","notify_location":"Singapore | New York | Dubai | Paris | London | Amsterdam | Sydney","notify_delay":"1000","notify_display":"4000","quick_view":true,"quick_view_in_mobile":false,"show_product_availability":true,"show_product_vendor":true,"show_product_sku":false,"show_product_review":false,"show_short_desc":true,"show_variant_swatches":true,"mailChimp_newsletter":"","newsletter_code":"","newsletter_popup":false,"nwptype":"pageload","newsletter_popup_time":"5000","newsletter_img":"","newsletter_popup_title":"Join Our Mailing List","newsletter_popup_title_color":"#000000","newsletter_popup_subtitle":"Sign Up for our exclusive email list and be the first to know about new products and special offers","show_social_icons":true,"checkout_header_image":"","checkout_logo_image":"shopify:\/\/shop_images\/FG_-_Transparent_Straight.png","checkout_logo_position":"center","checkout_logo_size":"large","checkout_body_background_image":"","checkout_body_background_color":"#fff","checkout_input_background_color_mode":"white","checkout_sidebar_background_image":"","checkout_sidebar_background_color":"#fafafa","checkout_heading_font":"Helvetica Neue","checkout_body_font":"Helvetica Neue","checkout_accent_color":"#1990c6","checkout_button_color":"#1990c6","checkout_error_color":"#ff6d6d","show_product_type":false,"lbl_new_color":"#000000","lbl_sale_color":"#ff708e","show_product_label":false,"image_swatches":false,"cart_bag_clr":"#000","search_ico_clr":"#000","nav_link_lbl_bg":"#31a3a3","type_header_family":"Google_Roboto+Slab_400_sans","type_base_family":"lato_n4","disable_newsletter_popup":false,"display_newsletter":true,"socia_icon_color":"#141515","display_facebook":true,"display_twitter":true,"display_pinterest":true,"display_instagram":true,"display_tumblr":true,"display_youtube":true,"display_vimeo":true,"type_bold_product_titles":false,"social_snapchat_link":"","is_layout_fullwidth":false,"is_header_fullwidth":true,"header_border_clr":"#e8e9eb","button_bg_clr":"#ffffff","button_text_clr":"#888888","product_filter_heading_clr":"#075159","is_layout_fullwidth?":true,"sections":{"header":{"type":"header","blocks":{"1594842716619":{"type":"single_link","settings":{"title":"HOME","url":"https:\/\/froggrips.myshopify.com\/"}},"1594625815808":{"type":"megamenu1","settings":{"title":"Shop","url":"shopify:\/\/collections\/all","mm_linklist":"shop","mmcolumns":1,"product_ttl":"","megamenu1_product":"","Image1url":"","custom_size":true,"mm_size":"300","mm_align":"right"}},"dc4b2e9d-f350-444a-8bec-51883e28b2c9":{"type":"dropdown","settings":{"title":"Customers","url":"shopify:\/\/pages\/faq","mm_linklist":"customers"}}},"block_order":["1594842716619","1594625815808","dc4b2e9d-f350-444a-8bec-51883e28b2c9"],"settings":{"boxedheader":true,"message":false,"message_mobile":false,"message_text":"","message_link":"shopify:\/\/collections\/all","promotion_view":"small","top_header":true,"top_header_mbl":true,"top_header_left_text":"<a style=\"padding-left:1em;\" target=\"_blank\" href=\"https:\/\/www.facebook.com\/sharer.php?u=https:\/\/froggrips.com.au\/products\/frog-tape-1\"><i class=\"ad ad-facebook-square\"><\/i> <\/a>\n<a style=\"padding-left:0.4em;\" target=\"_blank\" href=\"https:\/\/www.instagram.com\/Frog_grips\/\"><i class=\"ad ad-instagram\"><\/i><\/a>\n<a style=\"padding-left:0.7em;padding-right:1em;\" target=\"_blank\" href=\"https:\/\/froggrips.myshopify.com\/pages\/contact-us\"><i class=\"ad ad-envelope\"><\/i> <\/a> ","header_case":"uppercase","logo":"shopify:\/\/shop_images\/FG_-_Transparent_Straight_5efc9450-6e4e-4092-9b2e-91a998a81b30.png","logo_max_width":"60","align_logo":"left","menuarrow":false,"menuAlign":"center","nm_label1":"New","nm_label2":"Sale","nm_label3":"Hot","nm_label4":"Popular","nm_label5":"New"}},"slideshow":{"type":"slideshow","blocks":{"5469e241-e9a2-4d83-92ab-9d9dc06284fa":{"type":"image","settings":{"image":"shopify:\/\/shop_images\/Artboard_2.png","mb_image":"shopify:\/\/shop_images\/Artboard_2.png","alignment":"top","title":"","subheading":"BACK IN STOCK","slide_button_text":"Shop now","link":"shopify:\/\/collections\/grips","textalign":"left","vttextalign":"bottom"}},"c9526104-423a-45eb-85d4-32b912322353":{"type":"image","settings":{"image":"shopify:\/\/shop_images\/Untitled_design_32.png","mb_image":"shopify:\/\/shop_images\/Untitled_design_32.png","alignment":"top","title":"AUSTRALIA'S BEST ATHLETES","subheading":"USE FROG GRIP PRODUCTS!","slide_button_text":"JOIN THE FROG SQUAD","link":"shopify:\/\/collections\/all","textalign":"right","vttextalign":"bottom"}},"1596714403386":{"type":"image","settings":{"image":"shopify:\/\/shop_images\/Copy_of_Untitled_3.png","mb_image":"shopify:\/\/shop_images\/Copy_of_Untitled_5.png","alignment":"center","title":"Frog tape","subheading":"better HOOK GRIP, bigger lifts, all the colours!","slide_button_text":"buy frog tape!","link":"shopify:\/\/collections\/tape","textalign":"right","vttextalign":"bottom"}},"1599300262659":{"type":"image","settings":{"image":"shopify:\/\/shop_images\/Untitled_design_22.png","mb_image":"shopify:\/\/shop_images\/Untitled_design_22.png","alignment":"center","title":"NEW FIBRE GRIPS","subheading":"THE SOFTEST GRIPS! PERFECT FOR CHALKY USE","slide_button_text":"BUY NOW","link":"shopify:\/\/products\/fibre-grips","textalign":"left","vttextalign":"middle"}}},"block_order":["5469e241-e9a2-4d83-92ab-9d9dc06284fa","c9526104-423a-45eb-85d4-32b912322353","1596714403386","1599300262659"],"settings":{"fullwidth":true,"autoplay":true,"imageffect":true,"autoplay_speed":"5000","slideshow_height":"small","navigation":"arrow"}},"footer":{"type":"footer","blocks":{"1539946776936":{"type":"contact","settings":{"title":"","logo":"shopify:\/\/shop_images\/FG_-_Transparent_Straight_1.png","address":"","phone":"","email":"","show_socials":false,"socials_ttl":"Stay Connected"}},"1532932009490":{"type":"menu","settings":{"title":"Information","menulinks":"info"}},"1532934965624":{"type":"menu","settings":{"title":"Customer Services","menulinks":"cs"}},"1594626416705":{"type":"newsletter","settings":{"title":"SUBSCribe","sub_title":"Subscribe to get special offers, free giveaways, and once-in-a-lifetime deals."}}},"block_order":["1539946776936","1532932009490","1532934965624","1594626416705"],"settings":{"display_newsletter":false,"title":"<span>sign up for <\/span>newsletter","show_background":true,"show_socials":true,"copyright_text":"<img src=\"https:\/\/cdn.shopify.com\/s\/files\/1\/0432\/0355\/9579\/files\/FireShot_Capture_875_-_Get_Better_With_Bear_KompleX_-_www.bearkomplex.com.png?v=1594628142\">\n<br>\n<span>© 2020 FrogGrips .<\/span> All Rights Reserved.  <br>","show_payment_icons":false,"show_designby":false}},"cart-template":{"type":"cart-template","settings":{"style":"style1","display_saving":true,"cart_notes_enable":true,"shippingText":false,"additionalCheckout":true,"currency_display":false,"currency_note":"We processes all orders in [shop.currency]. While the content of your cart is currently displayed in [selected.currency], the checkout will use [shop.currency] at the most current exchange rate.","payment":"","shipping_calculator":false,"shipping_calculator_heading":"Get shipping estimates","shipping_calculator_default_country":"Australia","shipping_calculator_submit_button_label":"Calculate shipping","shipping_calculator_submit_button_label_disabled":"Calculating..."}},"product-template":{"type":"product-template","blocks":{"1574078308252":{"type":"descriptions","settings":{"title":"Product Details"}},"1574078311788":{"type":"review","settings":{"title":"Product Reviews"}}},"block_order":["1574078308252","1574078311788"],"settings":{"product_latyout":"style1","enable_zoom":true,"enable_lightbox":true,"thumbnail_pos":"left","show_product_navigation":true,"show_product_review":true,"show_saleoff":true,"show_product_availability":true,"show_product_vendor":false,"show_product_sku":false,"show_short_desc":true,"quantity_msg":false,"countdown":false,"askaboutproduct":true,"sticky_cart":true,"enable_payment_button":true,"show_share_buttons":true,"show_free_ship":false,"show_estimate_ship":false,"show_product_type":false,"show_collection":false,"show_tags":false,"sizechartlink":false,"sizechart_type":"default","sizechart_page":"","enable_360":false,"max_width_popup":400,"max_hegiht_popup":500,"show_variant_swatches":true,"color_type":"color","color_size":"medium","color_style":"rounded_rectangle","fake_orders":false,"orders":13,"orders_time":24,"orders_msg":"[orders] sold in last [hours] hours","fake_visitors":false,"visitors":50,"visitors_time":11,"visitors_msg":"[visitors] Persons looking for this product","image_banner":"","show_features":true,"feature1_icon":"","feature1_text":"","feature2_icon":"","feature2_text":"","feature3_icon":"","feature3_text":"","feature4_icon":"","feature4_text":"","show_product_tabs":true,"show_related_products":true,"related_products_autoplay":true,"related_title":"Related Products","related_sub_title":"","slider_related_speed":"5000","slider_related_animation_speed":"200","gridstyle":"style1","grid":"5","tablet-grid":"3","mobile-grid":"2","related_total_product_to_show":"6","show_viewed_products":false,"viewedproduct_title":"","viewedproduct_sub_title":"","rc_grid":"5","rc_tablet-grid":"3","rc_mobile-grid":"2","recent_total_product_to_show":"5"}},"collection-template":{"type":"collection-template","blocks":{"1532947274056":{"type":"categories","settings":{"title":"Categories","side_categories":"main-menu"}},"1532947285782":{"type":"filter_by","settings":{"title":"Price","filter_tags":"Under $50,\nUnder $100, \n$100 - $400, \n$400 - $600,\n$600 - $800,\nAbove $800","twocall":false}},"1532947752457":{"type":"filter_by","settings":{"title":"Size","filter_tags":"XS, S, M, L, XL, XXL","twocall":false}},"1532947567225":{"type":"by_color","settings":{"title":"Color","filter_tags":"Black, White, Red, Blue, Pink, Silver, Gray, Green, Orange, Marun, Yellow, Cyan, Gold, Purple, olive","image_swatches":false}},"1532947863384":{"type":"filter_by","settings":{"title":"Brands","filter_tags":"Allen Vela, Famiza, Oxymat, Vanelas, Pagini,\nMonark, Cantitate, Lirisla,\nZuzuva","twocall":false}},"1532947884050":{"type":"products","settings":{"title":"Popular Products","sidebar_products":"","num_of_products":"4","side_all_products":false}},"1532947919865":{"type":"image_bnr","settings":{"side_bnr_img":"","side_bnr_link":""}},"1532948004685":{"type":"static_text","settings":{"title":"Information","text":"<p>Use this text to share information about your brand with your customers. Describe a product, share announcements, or welcome customers to your store.<\/p>"}},"1532948070424":{"type":"pr_tags","settings":{"title":"Product Tags"}}},"block_order":["1532947274056","1532947285782","1532947752457","1532947567225","1532947863384","1532947884050","1532947919865","1532948004685","1532948070424"],"settings":{"show_collection_image":true,"show_vendor":false,"show_product_review":true,"sort_enable":true,"gridstyle":"style1","grid":"3","tablet-grid":"3","mobile-grid":"1","rows":"3","pagination":"infinite","sidebar_position":"nosidebar"}},"faq-template":{"type":"faq-template","blocks":{"1493994331036":{"type":"faqs","settings":{"question":"HOW MUCH IS SHIPPING?","answer":"Shipping Western Australia wide is $7\nShipping to the other states of Australia is $10\n\nThese rates are subject to change for special rural areas or price increases.\n\n."}},"1493994939248":{"type":"faqs","settings":{"question":"WHEN WILL MY ORDER BE SHIPPED?","answer":"All orders will be shipped in 1-2 buisness days.\nDelays may occur due to holidays or events on the calendar \n\nON OCCASION, ORDERS ARE HELD TO BE REVIEWED BY OUR TEAM; THESE ORDERS MAY BE SUBJECT TO SHIPMENT DELAYS."}},"1493994956959":{"type":"faqs","settings":{"question":"HOW LONG WILL IT TAKE FOR MY ORDER TO ARRIVE?","answer":"Order in Western Australia should arrive within in 1-2 weeks.\nAustralia wide orders 1-3 week \n\ndepending on location IE rural area\n\nON OCCASION, ORDERS ARE HELD TO BE REVIEWED BY OUR TEAM; THESE ORDERS MAY BE SUBJECT TO SHIPMENT DELAYS.\n\nFROG GRIPS IS NOT RESPONSIBLE FOR DELAYS IN SHIPPING OR DELIVERY THAT RESULT FROM FACTORS OUTSIDE OUR CONTROL SUCH AS INCLEMENT WEATHER, ACTS OF GOD, OR ANY OTHER SHIPPING-RELATED ISSUE(S)."}},"1594628550109":{"type":"faqs","settings":{"question":"I JUST PLACED MY ORDER.  CAN I STILL MAKE CHANGES TO MY CART?","answer":"UNFORTUNATELY ,ONCE AN ORDER HAS BEEN PLACED WE ARE UNABLE TO ADD OR REMOVE AN ITEM."}},"1594628597772":{"type":"faqs","settings":{"question":"CAN I CANCEL MY ORDER?","answer":"AS LONG AS THE ORDER HAS NOT BEEN SHIPPED, WE CAN CANCEL AND REFUND THE ORDER."}},"1594628646881":{"type":"faqs","settings":{"question":"CAN I UPDATE MY SHIPPING ADDRESS?","answer":"YES, AS LONG AS WE HAVEN'T SHIPPED THE ORDER WE CAN UPDATE THE SHIPPING ADDRESS."}},"1594628661276":{"type":"faqs","settings":{"question":"I DIDN'T RECEIVE AN CONFIRMATION EMAIL","answer":"ONCE THE ORDER HAS BEEN PLACED, YOU SHOULD RECEIVE AN CONFORMATION EMAIL. IF NOT, PLEASE CHECK YOUR JUNK MAIL FIRST BEFORE CONTACTING US."}},"1594628693191":{"type":"faqs","settings":{"question":"I PICKED THE WRONG SIZE, CAN I CHANGE IT AFTER I ORDERED?","answer":"AS LONG AS THE ORDER HAS NOT SHIPPED WE CAN ADJUST THE SIZE OR COLOR OF THE ITEM.\nPLEASE EMAIL US RIGHT AWAY WITH YOUR REQUEST. INCLUDE YOUR ORDER #, FIRST AND LAST NAME IN THE EMAIL. CONTACT US AT CONTACT@FROGGRIP.CO.AU"}}},"block_order":["1493994331036","1493994939248","1493994956959","1594628550109","1594628597772","1594628646881","1594628661276","1594628693191"],"settings":{}},"contact-template":{"type":"contact-template","settings":{"show_google_map":false,"map_title":"Our store","address":"<p>1714 Albany Highway, Kenwick, WA, 6107, Australia<\/p><p>Mon - Fri, 10am - 9pm<br\/>Saturday, Closed<br\/>Sunday, Closed<\/p>","map_address":"1714 albany highway, Kenwick, WA, 6107, Australia","show_button":true,"api_key":"AIzaSyD4SkQNHmK_XywhrWLWc4RxRomE19qHaqM","contact_title":"Drop Us A Line","contact_text_desc":"Check out our FAQs page for frequently asked questions. If you have any questions\/queries drop us a message below with your contact details and we will get back to you at the earliest.","show_labels":false,"contact_your_name":"Name","contact_phone_number":"Phone Number","contact_your_email":"Email","contact_your_comment":"Your Message","show_store_opening":true,"store_opening_time":"<strong>Always Opening <\/strong><br>","contact-address":"","phone":"","email":"help@froggrips.com","Show_location":true,"Show_Social_media":true}},"list-collections-template":{"type":"list-collections-template","blocks":{"1553924507482":{"type":"collection","settings":{"collection":"","collection_image":""}},"1553925521929":{"type":"collection","settings":{"collection":"","collection_image":""}},"1553925092268":{"type":"collection","settings":{"collection":"","collection_image":""}},"1553925776609":{"type":"collection","settings":{"collection":"","collection_image":""}},"1553925918852":{"type":"collection","settings":{"collection":"","collection_image":""}},"1553926113575":{"type":"collection","settings":{"collection":"","collection_image":""}},"1553926398736":{"type":"collection","settings":{"collection":"","collection_image":""}},"1553926515930":{"type":"collection","settings":{"collection":"","collection_image":""}}},"block_order":["1553924507482","1553925521929","1553925092268","1553925776609","1553925918852","1553926113575","1553926398736","1553926515930"],"settings":{"page_title":"Spring Summer Collection 2019","display_type":"selected","sort":"alphabetical","grid":"4"}},"blog-template":{"type":"blog-template","settings":{"layout":"grid","number_of_post_to_show":"4","sidebar_position":"nosidebar","blog_show_author":true,"blog_show_date":true,"show_category":true,"category_box_title":"Category","show_recent_posts":true,"recent_posts_title":"Recent Posts","show_banner_ad":true,"sidebar_banner":"","banner_link":"","show_products":true,"collection_title":"Trending Now","sidebar_collection":"","number_of_prodcut":"4"}},"lookbook-template":{"type":"lookbook-template","blocks":{"1494239838404":{"type":"lookbook1","settings":{"image":"","url":"#","title":"Women's Winter wear"}},"1494239974007":{"type":"lookbook1","settings":{"image":"","url":"#","title":"Collection 2017 special"}},"1494240001606":{"type":"lookbook1","settings":{"image":"","url":"#","title":"Summer Collection"}},"1494240023086":{"type":"lookbook1","settings":{"image":"","url":"#","title":"Kids Wear"}},"1494241006851":{"type":"lookbook2","settings":{"image":"","url":"#","title":"Shop Collection"}},"1494241168693":{"type":"lookbook2","settings":{"image":"","url":"#","title":"High Heel Shoes Collection"}},"1494241226929":{"type":"lookbook2","settings":{"image":"","url":"#","title":"Denim Jean's Collection"}},"1494241258389":{"type":"lookbook2","settings":{"image":"","url":"#","title":"Men's Watch New Arrival"}},"1494241326762":{"type":"lookbook2","settings":{"image":"","url":"#","title":"Hot Summer Collection"}},"1494241482971":{"type":"lookbook2","settings":{"image":"","url":"#","title":"Women jackets"}},"1494242856150":{"type":"lookbook1","settings":{"image":"","url":"#","title":"lingerie collection"}}},"block_order":["1494239838404","1494239974007","1494240001606","1494240023086","1494241006851","1494241168693","1494241226929","1494241258389","1494241326762","1494241482971","1494242856150"],"settings":{"layout_style":"lookbook1","btn_txt":"Shop The Collectons"}},"article-template":{"type":"article-template","settings":{"sidebar_position":"right","blog_show_author":false,"blog_show_date":true,"show_share_buttons":true,"show_category":false,"category_box_title":"Category","show_recent_posts":true,"recent_posts_title":"Recent Posts","show_banner_ad":false,"sidebar_banner":"","banner_link":"","show_products":true,"collection_title":"Trending Now","sidebar_collection":"tape","number_of_prodcut":"4"}},"about-us":{"type":"about-us","blocks":{"1537787539345":{"type":"image","settings":{"image":"shopify:\/\/shop_images\/Untitled_design_13.png","width":"50%","alignment":"center"}},"1594629116999":{"type":"html","settings":{"code":"<h1 class=\"hidden-xs\">    <\/h1> \n<h1 class=\"hidden-xs\">    <\/h1> \n<div style=\"text-align:center\">\n<br>\n<h1> Sean &amp; Mick \n<\/h1>\n<br>\n<p>\nMeet the men behind the Frog! \nMore than 10 years in CrossFit, 15+ in the fitness industry, Competing, Running competitions and 8 years+ owning a CrossFit affiliate, combined, we've seen it all. Our mission is to provide quality gear that solves problems, you, the athlete face day to day in training. Problems such as ripped hands, to sore knees to cruxes like chalking 50x a workout. All of which do nothing for progress! \n<\/p>\n<br>\n<a href=\"#\" class=\"btn\"> CONTACT US <\/a><a>\n<\/a>\n<\/div>","width":"50%"}},"1599362200118":{"type":"text","settings":{"title":"Enter the frog","text":"<p>Bringing fun, humour and education in our message and quality fitness gear to the functional fitness community. We're in the trenches with you on the quest to get better and we want our products to assist that journey. Whether you're a complete beginner or a seasoned professional. We want you to experience better with frog!<\/p>","width":"50%","alignment":"top-middle","align_text":"left"}},"1599362816769":{"type":"image","settings":{"image":"shopify:\/\/shop_images\/0C7A1192.JPG","width":"50%","alignment":"bottom-right"}},"1599364354973":{"type":"image","settings":{"image":"shopify:\/\/shop_images\/0C7A0796.JPG","width":"50%","alignment":"top-left"}},"1599364169120":{"type":"text","settings":{"title":"FROG SQUAD","text":"<p>Our goal is to ensure up and coming and established athletes in the Australian and New Zealand fitness scene are supported in their training to be the best they can be! <\/p>","width":"50%","alignment":"top-middle","align_text":"left"}}},"block_order":["1537787539345","1594629116999","1599362200118","1599362816769","1599364354973","1599364169120"],"settings":{"title":"THE FROG VIBE"}},"1540719779508":{"type":"products-slider","settings":{"title":"THE BEST GRIPS IN THE GAME","subtitle":"","collection":"grips","gridstyle":"style1","grid":"6","tablet-grid":"4","mobile-grid":"1","rows":"10","show_vendor":false,"show_product_review":true}},"sswreviewslider":{"type":"sswreviewslider","settings":{}},"top-information-bar":{"type":"top-information-bar","settings":{"topbarmobile":true}},"1594592005783":{"type":"instagram","disabled":true,"settings":{"instagram_title":"Follow Us!","instagram_des":"","instagram_button_text":"","instagram_button_link":"","user-id":"5362056112","accessToken":"5362056112.ba4c844.3960df2b3fc54f239207c6cd9bc84cb8","limit":"8","images_size":"low_resolution"}},"1594592047232":{"type":"store-features","blocks":{"1594592047232-0":{"type":"text_block","settings":{"icons":"ad-truck-l","title":"FREE U.S. SHIPPING","text":"<p>Free shipping in the USA and free worldwide shipping on order over $45.<\/p>"}},"1594592047232-1":{"type":"text_block","settings":{"icons":"ad-truck-l","title":"MONEY BACK GUARANTEE","text":"<p>Not satisfied with your improved workout? We&#x27;ll refund you within 30 days.<\/p>"}},"1594592047232-2":{"type":"text_block","settings":{"icons":"ad-truck-l","title":"QUALITY ASSURANCE ON ALL PRODUCTS","text":"<p>Quality is what sets us apart.<\/p>"}},"1594592058316":{"type":"text_block","settings":{"icons":"ad-truck-l","title":"SAFE PAYMENTS","text":"<p>Secured payment. Money back guarantee.<\/p><p><\/p>"}}},"block_order":["1594592047232-0","1594592047232-1","1594592047232-2","1594592058316"],"disabled":true,"settings":{"enable_icons":false,"icons_clr":"#000000"}},"1594592744401":{"type":"custom-content","blocks":{"1594592764929":{"type":"html","settings":{"code":"","width":"100%"}}},"block_order":["1594592764929"],"settings":{"top-offeset":"default","title":"","subtitle":"","gridstyle":"style3"}},"1594622237370":{"type":"featured-product","disabled":true,"settings":{"featured_product_lbl":"","featured_product":"gymnastic-grip-pair","image_size":"medium","show_vendor":false,"show_product_review":true,"show_short_des":true,"enable_zoom":false,"show_share_buttons":true,"show_variant_swatches":true,"color_type":"color","color_size":"medium","color_style":"rectangle","fake_orders":false,"orders":20,"orders_time":24,"orders_msg":"[orders] sold in last [hours] hours"}},"1594630411912":{"type":"hero","disabled":true,"settings":{"parallax_scroll":true,"image":"shopify:\/\/shop_images\/Untitled_design_5.png","alignment":"top","textalign":"left","title":"","text":"","hero_size":"small","text_size":"large","font-weight":"bold","button_label":"STEP INTO THE JUNGLE","button_link":"shopify:\/\/collections\/tape"}},"1594630881349":{"type":"logo-bar","blocks":{"1594630881349-2":{"type":"logo_image","settings":{"image":"shopify:\/\/shop_images\/download_2.png","link":""}},"1594630881349-3":{"type":"logo_image","settings":{"image":"shopify:\/\/shop_images\/6bcff229aa87d63b24ea7867aa194f86.png","link":""}},"1594630881349-5":{"type":"logo_image","settings":{"image":"shopify:\/\/shop_images\/ff02b2ccb2f7b0cbcb2f260dcb9f5265.jpg","link":""}}},"block_order":["1594630881349-2","1594630881349-3","1594630881349-5"],"disabled":true,"settings":{"title":"Our Brands","subtitle":"","grid":3,"tablet-grid":3,"mobile-grid":2}},"1594631015438":{"type":"custom-content","blocks":{"1594631015438-1":{"type":"image","settings":{"image":"shopify:\/\/shop_images\/download_2.png","width":"33%"}},"1594631043426":{"type":"image","settings":{"image":"shopify:\/\/shop_images\/6bcff229aa87d63b24ea7867aa194f86.png","width":"33%"}},"1594631058515":{"type":"image","settings":{"image":"shopify:\/\/shop_images\/Untitled-1.jpg","width":"33%"}}},"block_order":["1594631015438-1","1594631043426","1594631058515"],"disabled":true,"settings":{"top-offeset":"default","title":"","subtitle":"","gridstyle":"style1"}},"password":{"type":"password","settings":{"logo":"shopify:\/\/shop_images\/FG_-_Transparent_Straight_5efc9450-6e4e-4092-9b2e-91a998a81b30.png","logo_max_width":"100","bg_clr":"","bg_img":"shopify:\/\/shop_images\/117313430_743576526437849_1332896982616991249_n.jpg","txt_clr":"","header":"Coming Soon","newsletter_enable":true,"newsletter_form_heading":"Be the first to know when we launch.","newsletter_placeholder":"Email address","newsletter_button_text":"Notify me","show_share_buttons":true,"social_message":"Spread the word"}},"1594824715356":{"type":"instafeed","settings":{"heading_size":22,"feed_width":95,"html_area":"<!-- -->"}},"0f6ac504-ec7d-4279-b35b-e8b526e83aa3":{"type":"image-slideshow","blocks":{"0f6ac504-ec7d-4279-b35b-e8b526e83aa3-16838037605c4d0ce1-0":{"type":"image","settings":{"image":"shopify:\/\/shop_images\/TRUSTED_BY_THE_BEST_IN_THE_BUSINESS_1.png","link":""}},"0f6ac504-ec7d-4279-b35b-e8b526e83aa3-16838037605c4d0ce1-1":{"type":"image","settings":{"image":"shopify:\/\/shop_images\/Copy_of_TRUSTED_BY_THE_BEST_IN_THE_BUSINESS.png","link":""}},"47e3383a-4baa-471b-bc53-d18ceb3679c7":{"type":"image","settings":{"image":"shopify:\/\/shop_images\/Copy_of_TRUSTED_BY_THE_BEST_IN_THE_BUSINESS_7604291d-ead6-4fee-9802-3a7489d9019a.png","link":""}}},"block_order":["0f6ac504-ec7d-4279-b35b-e8b526e83aa3-16838037605c4d0ce1-0","0f6ac504-ec7d-4279-b35b-e8b526e83aa3-16838037605c4d0ce1-1","47e3383a-4baa-471b-bc53-d18ceb3679c7"],"settings":{"show_slideshow":"desktop_mobile","autoplay":true,"autoplay_speed":"5000"}}},"content_for_index":["slideshow","1594630411912","1594592744401","0f6ac504-ec7d-4279-b35b-e8b526e83aa3","1540719779508","sswreviewslider","1594631015438","1594592047232","1594824715356","1594622237370","1594592005783","1594630881349"],"blocks":{"1606158967485095091":{"type":"shopify:\/\/apps\/wholesale-gorilla\/blocks\/wsg-header\/c48d0487-dff9-41a4-94c8-ec6173fe8b8d","disabled":false,"settings":{"embed_bg_color":"#000000","embed_text_color":"#000000"}},"6588702529468458379":{"type":"shopify:\/\/apps\/ecomposer-builder\/blocks\/app-embed\/a0fc26e1-7741-4773-8b27-39389b4fb4a0","disabled":false,"settings":{}}}},"presets":{"Default":{"color_text":"#3d4246","color_body_text":"#788188","color_sale_text":"#7796A8","color_borders":"#e8e9eb","color_button":"#7796A8","color_button_text":"#fff","color_small_button":"#fff","color_small_button_text":"#3d4246","color_text_field":"#fff","color_text_field_text":"#000","color_image_overlay_text":"#fff","color_image_overlay":"#3d4246","image_overlay_opacity":"0.25","color_body_bg":"#fff","type_header_family":"Google_Work+Sans_600_sans","type_header_base_size":"26px","type_base_family":"Google_Work+Sans_400_sans","type_base_size":"16px","type_bold_product_titles":false,"share_facebook":true,"share_twitter":true,"share_pinterest":true,"sections":{"header":{"type":"header","settings":{}},"hero":{"type":"hero","settings":{"text_size":"large"}},"slideshow":{"type":"slideshow","blocks":{"slideshow-0":{"type":"image","settings":{}},"slideshow-1":{"type":"image","settings":{}}},"block_order":["slideshow-0","slideshow-1"],"settings":{}},"feature-row":{"type":"feature-row","settings":{}},"footer":{"type":"footer","settings":{}}},"content_for_index":["hero","feature-row","slideshow"]}}}